flowscale/__init__.py
flowscale/api.py
flowscale/types.py
flowscale-1.1.4.dist-info/METADATA
flowscale-1.1.4.dist-info/WHEEL
flowscale-1.1.4.dist-info/RECORD
