Metadata-Version: 2.4
Name: flowscale
Version: 1.1.4
Summary: A Python library for communicating with the Flowscale APIs
Project-URL: Homepage, https://github.com/flowscale/flowscale-python
Author-email: flowscale <rupayan@example.com>
License: MIT
Classifier: License :: OSI Approved :: MIT License
Classifier: Operating System :: OS Independent
Classifier: Programming Language :: Python :: 3
Requires-Python: >=3.13
Requires-Dist: requests>=2.25.0
